sgr_commhandler/__init__.py
sgr_commhandler/declaration_library.py
sgr_commhandler/device_builder.py
sgr_commhandler/api/__init__.py
sgr_commhandler/api/configuration_parameter.py
sgr_commhandler/api/data_point_api.py
sgr_commhandler/api/data_types.py
sgr_commhandler/api/device_api.py
sgr_commhandler/api/dynamic_parameter.py
sgr_commhandler/api/functional_profile_api.py
sgr_commhandler/driver/__init__.py
sgr_commhandler/driver/contact/__init__.py
sgr_commhandler/driver/contact/contact_interface_async.py
sgr_commhandler/driver/generic/__init__.py
sgr_commhandler/driver/generic/generic_interface_async.py
sgr_commhandler/driver/messaging/__init__.py
sgr_commhandler/driver/messaging/messaging_client_async.py
sgr_commhandler/driver/messaging/messaging_filter.py
sgr_commhandler/driver/messaging/messaging_interface_async.py
sgr_commhandler/driver/modbus/__init__.py
sgr_commhandler/driver/modbus/modbus_client_async.py
sgr_commhandler/driver/modbus/modbus_interface_async.py
sgr_commhandler/driver/modbus/payload_decoder.py
sgr_commhandler/driver/modbus/shared_client.py
sgr_commhandler/driver/rest/__init__.py
sgr_commhandler/driver/rest/authentication.py
sgr_commhandler/driver/rest/request.py
sgr_commhandler/driver/rest/restapi_interface_async.py
sgr_commhandler/utils/__init__.py
sgr_commhandler/utils/jmespath_mapping.py
sgr_commhandler/utils/template.py
sgr_commhandler/utils/value_util.py
sgr_commhandler/validators/__init__.py
sgr_commhandler/validators/resolver.py
sgr_commhandler/validators/validator.py
sgr_commhandler-0.5.0.dist-info/licenses/LICENSE.md
sgr_commhandler-0.5.0.dist-info/METADATA
sgr_commhandler-0.5.0.dist-info/WHEEL
sgr_commhandler-0.5.0.dist-info/top_level.txt
sgr_commhandler-0.5.0.dist-info/RECORD
