Metadata-Version: 2.4
Name: sgr-commhandler
Version: 0.5.0
Summary: SmartGridready CommHandler Library
Author: Robin Schoch, Matthias Krebs
Maintainer: Matthias Krebs
License-Expression: BSD-3-Clause
Project-URL: Homepage, https://www.smartgridready.ch/
Project-URL: Documentation, https://smartgridready.github.io/SGrPython/docs/commhandler/
Project-URL: Repository, https://github.com/SmartGridready/SGrPython.git
Project-URL: Issues, https://github.com/SmartGridready/SGrPython/issues
Project-URL: Changelog, https://github.com/SmartGridready/SGrPython/blob/master/commhandler/CHANGELOG.md
Requires-Python: >=3.9
License-File: LICENSE.md
Requires-Dist: Jinja2<4.0.0,>=3.1.0
Requires-Dist: jmespath<2.0.0,>=1.0.0
Requires-Dist: jsonata-python<1.0.0,>=0.6.0
Requires-Dist: parsel<1.11.0,>=1.10.0
Requires-Dist: pymodbus<3.8.0,>=3.7.0
Requires-Dist: gmqtt<1.0.0,>=0.7.0
Requires-Dist: xsdata<26.0.0,>=25.0.0
Requires-Dist: xmlschema<5.0.0,>=4.1.0
Requires-Dist: aiohttp<4.0.0,>=3.12.0
Requires-Dist: certifi
Requires-Dist: cachetools<7.0.0,>=6.2.0
Requires-Dist: sgr-specification<3.0.0,>=2.2.0
Dynamic: license-file
